RW/Core.py
RW/platform.py
RW/proxy.py
rw_devtools-0.0.8.dist-info/LICENSE
rw_devtools-0.0.8.dist-info/METADATA
rw_devtools-0.0.8.dist-info/WHEEL
rw_devtools-0.0.8.dist-info/top_level.txt
rw_devtools-0.0.8.dist-info/RECORD
