Metadata-Version: 2.1
Name: rw-devtools
Version: 0.0.8
Summary: A set of RunWhen Developer keywords and python libraries for local development
Home-page: https://github.com/runwhen-contrib/codecollection-devtools
Author: RunWhen
Author-email: info@runwhen.com
License: Apache License 2.0
Classifier: Programming Language :: Python :: 3
Classifier: License :: OSI Approved :: Apache Software License
License-File: LICENSE
Requires-Dist: jinja2 >=3.1.4
Requires-Dist: jmespath >=1.0.1
Requires-Dist: python-dateutil >=2.9.0
Requires-Dist: pyyaml >=6.0.1
Requires-Dist: requests >=2.31.0
Requires-Dist: robotframework >=4.1.2
Requires-Dist: rw-cli-keywords >=0.0.18
Requires-Dist: rw-devtools >=0.0.2
Requires-Dist: thefuzz >=0.20.0
